hydrolib/__init__.py
hydrolib/core/__init__.py
hydrolib/core/base/__init__.py
hydrolib/core/base/file_manager.py
hydrolib/core/base/models.py
hydrolib/core/base/parser.py
hydrolib/core/base/serializer.py
hydrolib/core/base/utils.py
hydrolib/core/basemodel.py
hydrolib/core/config.py
hydrolib/core/dflowfm/__init__.py
hydrolib/core/dflowfm/bc/__init__.py
hydrolib/core/dflowfm/bc/models.py
hydrolib/core/dflowfm/cmp/__init__.py
hydrolib/core/dflowfm/cmp/models.py
hydrolib/core/dflowfm/cmp/parser.py
hydrolib/core/dflowfm/cmp/serializer.py
hydrolib/core/dflowfm/common/__init__.py
hydrolib/core/dflowfm/common/models.py
hydrolib/core/dflowfm/crosssection/__init__.py
hydrolib/core/dflowfm/crosssection/models.py
hydrolib/core/dflowfm/ext/__init__.py
hydrolib/core/dflowfm/ext/models.py
hydrolib/core/dflowfm/extold/__init__.py
hydrolib/core/dflowfm/extold/common_io.py
hydrolib/core/dflowfm/extold/data/header.txt
hydrolib/core/dflowfm/extold/data/old-external-forcing-data.yaml
hydrolib/core/dflowfm/extold/models.py
hydrolib/core/dflowfm/extold/parser.py
hydrolib/core/dflowfm/extold/serializer.py
hydrolib/core/dflowfm/friction/__init__.py
hydrolib/core/dflowfm/friction/models.py
hydrolib/core/dflowfm/gui/__init__.py
hydrolib/core/dflowfm/gui/models.py
hydrolib/core/dflowfm/ini/__init__.py
hydrolib/core/dflowfm/ini/io_models.py
hydrolib/core/dflowfm/ini/models.py
hydrolib/core/dflowfm/ini/parser.py
hydrolib/core/dflowfm/ini/serializer.py
hydrolib/core/dflowfm/ini/util.py
hydrolib/core/dflowfm/inifield/__init__.py
hydrolib/core/dflowfm/inifield/models.py
hydrolib/core/dflowfm/mdu/__init__.py
hydrolib/core/dflowfm/mdu/legacy.py
hydrolib/core/dflowfm/mdu/models.py
hydrolib/core/dflowfm/net/__init__.py
hydrolib/core/dflowfm/net/models.py
hydrolib/core/dflowfm/net/reader.py
hydrolib/core/dflowfm/net/ugrid_conventions.json
hydrolib/core/dflowfm/net/writer.py
hydrolib/core/dflowfm/obs/__init__.py
hydrolib/core/dflowfm/obs/models.py
hydrolib/core/dflowfm/obscrosssection/__init__.py
hydrolib_core-0.10.1.dist-info/LICENSE
hydrolib_core-0.10.1.dist-info/METADATA
hydrolib_core-0.10.1.dist-info/WHEEL
hydrolib_core-0.10.1.dist-info/entry_points.txt
hydrolib_core-0.10.1.dist-info/RECORD
