Metadata-Version: 2.1
Name: hydrolib-core
Version: 0.10.1
Summary: Python wrappers around D-HYDRO Suite.
Home-page: https://deltares.github.io/HYDROLIB-core
License: MIT
Author: Deltares
Requires-Python: >=3.9,<4
Classifier: License :: OSI Approved :: MIT License
Classifier: Programming Language :: Python :: 3
Classifier: Programming Language :: Python :: 3.9
Classifier: Programming Language :: Python :: 3.10
Classifier: Programming Language :: Python :: 3.11
Classifier: Programming Language :: Python :: 3.12
Classifier: Programming Language :: Python :: 3.13
Provides-Extra: examples
Provides-Extra: plot
Requires-Dist: geopandas (>=1.0.0,<2.0.0) ; extra == "examples"
Requires-Dist: ipykernel (>=6.15.0,<7.0.0) ; extra == "examples"
Requires-Dist: jupyter (>=1.0.0,<2.0.0) ; extra == "examples"
Requires-Dist: lxml (>=5.0,<6.0)
Requires-Dist: matplotlib (>=3.8,<4.0) ; extra == "plot"
Requires-Dist: meshkernel (>=8.1.3,<9.0.0)
Requires-Dist: netCDF4 (>=1.5,<2.0,!=1.7.0,!=1.7.1)
Requires-Dist: numpy (>=1.25,<3) ; python_version >= "3.9" and python_version < "4.0"
Requires-Dist: numpy (>=2.1,<3.0) ; python_version >= "3.13" and python_version < "4.0"
Requires-Dist: openpyxl (>=3.0.9,<4.0.0) ; extra == "examples"
Requires-Dist: pandas (>=2.0.0,<3.0.0)
Requires-Dist: pydantic (>=2.5,<3.0)
Requires-Dist: pyyaml (>=6.0.2,<7.0.0)
Requires-Dist: strenum (>=0,<1)
Requires-Dist: tqdm (>=4.67.1,<5.0.0)
Project-URL: Documentation, https://deltares.github.io/HYDROLIB-core
Project-URL: Repository, https://github.com/deltares/hydrolib-core
Project-URL: issue tracker, https://github.com/Deltares/HYDROLIB-core/issues
